Workbook

Sheet Cover
B2: Hoa Phat Group (HPG) - FCFF DCF Model
B3: Academic equity research model | Prepared by Nguyen Vu Truong Huy | 11 Jun 2026
B5: Model Snapshot
B6: Ticker | C6: HPG VN
B7: Company | C7: Hoa Phat Group JSC
B8: Exchange | C8: HOSE
B9: Sector | C9: Steel & Industrial Materials
B10: Recommendation | C10: BUY
B11: Base-case target price | C11: =DCF!F18
B12: Market price used | C12: =Assumptions!C14
B13: Implied upside | C13: =DCF!F19
B16: Workbook Tabs
B17: Assumptions | C17: Editable drivers: revenue, margins, WACC, terminal growth, net debt, shares, spot price.
B18: Operating Forecast | C18: FY2024A-FY2030E operating bridge and FCFF build.
B19: DCF | C19: PV of FCFF, terminal value, EV, equity value, target price, upside.
B20: Scenarios | C20: Bear/base/bull assumption set and implied valuation range.
B21: Sensitivity | C21: Target price matrix across WACC and terminal growth.
B22: Comps | C22: Peer multiple cross-check for reasonableness.
B23: Sources | C23: Public source log and modeling notes.
B26: Disclaimer
B27: This model is an academic exercise and not investment advice. Inputs are editable and should be refreshed before use.

Sheet Assumptions
B2: Assumptions
B3: Blue/yellow cells are editable inputs; formula tabs link back to this sheet.
B5: General Inputs | F5: Projection Drivers
B6: Model date | C6: 11-Jun-2026 | D6: Source: model build date | F6: Metric | G6: FY2026E | H6: FY2027E | I6: FY2028E | J6: FY2029E | K6: FY2030E
B7: Currency | C7: VND bn unless stated | D7: Source: convention | F7: Revenue growth | G7: 0.28 | H7: 0.15 | I7: 0.09 | J7: 0.06 | K7: 0.04
B8: FY2025 revenue | C8: 158330 | D8: Source: public 2025 result references; VND bn | F8: EBITDA margin | G8: 0.142 | H8: 0.151 | I8: 0.158 | J8: 0.162 | K8: 0.162
B9: FY2025 EBITDA margin | C9: 0.132 | D9: Source: modeled from public margin/earnings direction | F9: D&A / revenue | G9: 0.044 | H9: 0.042 | I9: 0.04 | J9: 0.038 | K9: 0.036
B10: FY2025 D&A / revenue | C10: 0.045 | D10: Source: model estimate | F10: Capex / revenue | G10: 0.095 | H10: 0.075 | I10: 0.058 | J10: 0.048 | K10: 0.043
B11: Tax rate | C11: 0.2 | D11: Source: Vietnam statutory corporate tax assumption | F11: NWC / revenue change | G11: 0.075 | H11: 0.075 | I11: 0.07 | J11: 0.065 | K11: 0.065
B12: Net debt | C12: 52000 | D12: Source: model estimate, VND bn; adjusted for valuation framework consistency
B13: Diluted shares | C13: 6400 | D13: Source: model estimate, million shares
B14: Market price | C14: 23600 | D14: Source: public market price near 10-Jun-2026, VND/share
F15: Scenario Controls
F16: Scenario | G16: FY2026 growth | H16: Terminal EBITDA margin | I16: WACC | J16: Terminal growth
B17: DCF Inputs | F17: Bear | G17: 0.23 | H17: 0.145 | I17: 0.12 | J17: 0.02
B18: WACC | C18: 0.106 | D18: Base-case discount rate used in DCF sensitivity range | F18: Base | G18: 0.28 | H18: 0.162 | I18: 0.106 | J18: 0.03
B19: Terminal growth | C19: 0.03 | D19: Nominal long-term FCFF growth | F19: Bull | G19: 0.33 | H19: 0.175 | I19: 0.1 | J19: 0.035
B20: Mid-year convention | C20: No | D20: Year-end discounting used for simplicity

Sheet Operating Forecast
B2: Operating Forecast
B3: FY2024A-FY2030E operating bridge and free cash flow to firm.
C5: FY2024A | D5: FY2025A | E5: FY2026E | F5: FY2027E | G5: FY2028E | H5: FY2029E | I5: FY2030E
B6: Revenue | C6: 140560 | D6: =Assumptions!C8 | E6: =D6*(1+Assumptions!G7) | F6: =E6*(1+Assumptions!H7) | G6: =F6*(1+Assumptions!I7) | H6: =G6*(1+Assumptions!J7) | I6: =H6*(1+Assumptions!K7)
B7: Revenue growth | D7: =D6/C6-1 | E7: =E6/D6-1 | F7: =F6/E6-1 | G7: =G6/F6-1 | H7: =H6/G6-1 | I7: =I6/H6-1
B8: EBITDA | C8: =C6*12.8% | D8: =D6*Assumptions!C9 | E8: =E6*Assumptions!G8 | F8: =F6*Assumptions!H8 | G8: =G6*Assumptions!I8 | H8: =H6*Assumptions!J8 | I8: =I6*Assumptions!K8
B9: EBITDA margin | C9: =C8/C6 | D9: =D8/D6 | E9: =E8/E6 | F9: =F8/F6 | G9: =G8/G6 | H9: =H8/H6 | I9: =I8/I6
B10: D&A | C10: =C6*4.6% | D10: =D6*Assumptions!C10 | E10: =E6*Assumptions!G9 | F10: =F6*Assumptions!H9 | G10: =G6*Assumptions!I9 | H10: =H6*Assumptions!J9 | I10: =I6*Assumptions!K9
B11: EBIT | C11: =C8-C10 | D11: =D8-D10 | E11: =E8-E10 | F11: =F8-F10 | G11: =G8-G10 | H11: =H8-H10 | I11: =I8-I10
B12: Tax on EBIT | C12: =C11*Assumptions!$C$11 | D12: =D11*Assumptions!$C$11 | E12: =E11*Assumptions!$C$11 | F12: =F11*Assumptions!$C$11 | G12: =G11*Assumptions!$C$11 | H12: =H11*Assumptions!$C$11 | I12: =I11*Assumptions!$C$11
B13: NOPAT | C13: =C11-C12 | D13: =D11-D12 | E13: =E11-E12 | F13: =F11-F12 | G13: =G11-G12 | H13: =H11-H12 | I13: =I11-I12
B14: Capex | C14: =C6*8.0% | D14: =D6*8.0% | E14: =E6*Assumptions!G10 | F14: =F6*Assumptions!H10 | G14: =G6*Assumptions!I10 | H14: =H6*Assumptions!J10 | I14: =I6*Assumptions!K10
B15: Change in NWC | C15: =C6*6.5% | D15: =D6*6.5% | E15: =(E6-D6)*Assumptions!G11 | F15: =(F6-E6)*Assumptions!H11 | G15: =(G6-F6)*Assumptions!I11 | H15: =(H6-G6)*Assumptions!J11 | I15: =(I6-H6)*Assumptions!K11
B16: FCFF | C16: =C13+C10-C14-C15 | D16: =D13+D10-D14-D15 | E16: =E13+E10-E14-E15 | F16: =F13+F10-F14-F15 | G16: =G13+G10-G14-G15 | H16: =H13+H10-H14-H15 | I16: =I13+I10-I14-I15

Sheet DCF
B2: DCF Valuation
B3: FCFF discounted at WACC with Gordon-growth terminal value.
C5: FY2026E | D5: FY2027E | E5: FY2028E | F5: FY2029E | G5: FY2030E
B6: FCFF | C6: ='Operating Forecast'!E16 | D6: ='Operating Forecast'!F16 | E6: ='Operating Forecast'!G16 | F6: ='Operating Forecast'!H16 | G6: ='Operating Forecast'!I16
B7: Discount period | C7: 1 | D7: 2 | E7: 3 | F7: 4 | G7: 5
B8: Discount factor | C8: =1/(1+Assumptions!$C$18)^C7 | D8: =1/(1+Assumptions!$C$18)^D7 | E8: =1/(1+Assumptions!$C$18)^E7 | F8: =1/(1+Assumptions!$C$18)^F7 | G8: =1/(1+Assumptions!$C$18)^G7
B9: PV of FCFF | C9: =C6*C8 | D9: =D6*D8 | E9: =E6*E8 | F9: =F6*F8 | G9: =G6*G8
B12: Valuation Bridge
B13: PV explicit FCFF | C13: =SUM(C9:G9)
B14: Terminal FCFF | C14: =G6*(1+Assumptions!$C$19)
B15: Terminal value | C15: =C14/(Assumptions!$C$18-Assumptions!$C$19)
B16: PV terminal value | C16: =C15*G8 | F16: Target price
B17: Enterprise value | C17: =C13+C16 | F17: =C21
B18: Less: net debt | C18: =Assumptions!$C$12 | F18: =C21
B19: Equity value | C19: =C17-C18 | F19: =C22
B20: Fair value / share | C20: =C19/Assumptions!$C$13*1000
B21: Rounded target price | C21: =ROUND(C20,-3)
B22: Upside / downside | C22: =C21/Assumptions!$C$14-1

Sheet Scenarios
B2: Scenario Analysis
B3: Bear/base/bull framework; formulas approximate DCF output under alternative assumptions.
B5: Scenario | C5: FY2026 Revenue Growth | D5: Terminal EBITDA Margin | E5: WACC | F5: Terminal Growth | G5: Target Price | H5: Upside / Downside
B6: =Assumptions!F17 | C6: =Assumptions!G17 | D6: =Assumptions!H17 | E6: =Assumptions!I17 | F6: =Assumptions!J17 | G6: =ROUND(DCF!$C$21*(1+(D6-Assumptions!$H$18)*4+(E6-Assumptions!$I$18)*-5+(F6-Assumptions!$J$18)*7),-3) | H6: =G6/Assumptions!$C$14-1
B7: =Assumptions!F18 | C7: =Assumptions!G18 | D7: =Assumptions!H18 | E7: =Assumptions!I18 | F7: =Assumptions!J18 | G7: =ROUND(DCF!$C$21*(1+(D7-Assumptions!$H$18)*4+(E7-Assumptions!$I$18)*-5+(F7-Assumptions!$J$18)*7),-3) | H7: =G7/Assumptions!$C$14-1
B8: =Assumptions!F19 | C8: =Assumptions!G19 | D8: =Assumptions!H19 | E8: =Assumptions!I19 | F8: =Assumptions!J19 | G8: =ROUND(DCF!$C$21*(1+(D8-Assumptions!$H$18)*4+(E8-Assumptions!$I$18)*-5+(F8-Assumptions!$J$18)*7),-3) | H8: =G8/Assumptions!$C$14-1

Sheet Sensitivity
B2: Sensitivity
B3: Target price sensitivity to WACC and terminal growth.
B5: WACC \ Terminal growth | C5: 0.02 | D5: 0.025 | E5: 0.03 | F5: 0.035 | G5: 0.04
B6: 0.1 | C6: =ROUND(((SUM(DCF!C9:G9)+(DCF!G6*(1+C$5)/($B6-C$5))*DCF!G8)-Assumptions!$C$12)/Assumptions!$C$13*1000,-3) | D6: =ROUND(((SUM(DCF!C9:G9)+(DCF!G6*(1+D$5)/($B6-D$5))*DCF!G8)-Assumptions!$C$12)/Assumptions!$C$13*1000,-3) | E6: =ROUND(((SUM(DCF!C9:G9)+(DCF!G6*(1+E$5)/($B6-E$5))*DCF!G8)-Assumptions!$C$12)/Assumptions!$C$13*1000,-3) | F6: =ROUND(((SUM(DCF!C9:G9)+(DCF!G6*(1+F$5)/($B6-F$5))*DCF!G8)-Assumptions!$C$12)/Assumptions!$C$13*1000,-3) | G6: =ROUND(((SUM(DCF!C9:G9)+(DCF!G6*(1+G$5)/($B6-G$5))*DCF!G8)-Assumptions!$C$12)/Assumptions!$C$13*1000,-3)
B7: 0.105 | C7: =ROUND(((SUM(DCF!C9:G9)+(DCF!G6*(1+C$5)/($B7-C$5))*DCF!G8)-Assumptions!$C$12)/Assumptions!$C$13*1000,-3) | D7: =ROUND(((SUM(DCF!C9:G9)+(DCF!G6*(1+D$5)/($B7-D$5))*DCF!G8)-Assumptions!$C$12)/Assumptions!$C$13*1000,-3) | E7: =ROUND(((SUM(DCF!C9:G9)+(DCF!G6*(1+E$5)/($B7-E$5))*DCF!G8)-Assumptions!$C$12)/Assumptions!$C$13*1000,-3) | F7: =ROUND(((SUM(DCF!C9:G9)+(DCF!G6*(1+F$5)/($B7-F$5))*DCF!G8)-Assumptions!$C$12)/Assumptions!$C$13*1000,-3) | G7: =ROUND(((SUM(DCF!C9:G9)+(DCF!G6*(1+G$5)/($B7-G$5))*DCF!G8)-Assumptions!$C$12)/Assumptions!$C$13*1000,-3)
B8: 0.112 | C8: =ROUND(((SUM(DCF!C9:G9)+(DCF!G6*(1+C$5)/($B8-C$5))*DCF!G8)-Assumptions!$C$12)/Assumptions!$C$13*1000,-3) | D8: =ROUND(((SUM(DCF!C9:G9)+(DCF!G6*(1+D$5)/($B8-D$5))*DCF!G8)-Assumptions!$C$12)/Assumptions!$C$13*1000,-3) | E8: =ROUND(((SUM(DCF!C9:G9)+(DCF!G6*(1+E$5)/($B8-E$5))*DCF!G8)-Assumptions!$C$12)/Assumptions!$C$13*1000,-3) | F8: =ROUND(((SUM(DCF!C9:G9)+(DCF!G6*(1+F$5)/($B8-F$5))*DCF!G8)-Assumptions!$C$12)/Assumptions!$C$13*1000,-3) | G8: =ROUND(((SUM(DCF!C9:G9)+(DCF!G6*(1+G$5)/($B8-G$5))*DCF!G8)-Assumptions!$C$12)/Assumptions!$C$13*1000,-3)
B9: 0.12 | C9: =ROUND(((SUM(DCF!C9:G9)+(DCF!G6*(1+C$5)/($B9-C$5))*DCF!G8)-Assumptions!$C$12)/Assumptions!$C$13*1000,-3) | D9: =ROUND(((SUM(DCF!C9:G9)+(DCF!G6*(1+D$5)/($B9-D$5))*DCF!G8)-Assumptions!$C$12)/Assumptions!$C$13*1000,-3) | E9: =ROUND(((SUM(DCF!C9:G9)+(DCF!G6*(1+E$5)/($B9-E$5))*DCF!G8)-Assumptions!$C$12)/Assumptions!$C$13*1000,-3) | F9: =ROUND(((SUM(DCF!C9:G9)+(DCF!G6*(1+F$5)/($B9-F$5))*DCF!G8)-Assumptions!$C$12)/Assumptions!$C$13*1000,-3) | G9: =ROUND(((SUM(DCF!C9:G9)+(DCF!G6*(1+G$5)/($B9-G$5))*DCF!G8)-Assumptions!$C$12)/Assumptions!$C$13*1000,-3)
B10: 0.125 | C10: =ROUND(((SUM(DCF!C9:G9)+(DCF!G6*(1+C$5)/($B10-C$5))*DCF!G8)-Assumptions!$C$12)/Assumptions!$C$13*1000,-3) | D10: =ROUND(((SUM(DCF!C9:G9)+(DCF!G6*(1+D$5)/($B10-D$5))*DCF!G8)-Assumptions!$C$12)/Assumptions!$C$13*1000,-3) | E10: =ROUND(((SUM(DCF!C9:G9)+(DCF!G6*(1+E$5)/($B10-E$5))*DCF!G8)-Assumptions!$C$12)/Assumptions!$C$13*1000,-3) | F10: =ROUND(((SUM(DCF!C9:G9)+(DCF!G6*(1+F$5)/($B10-F$5))*DCF!G8)-Assumptions!$C$12)/Assumptions!$C$13*1000,-3) | G10: =ROUND(((SUM(DCF!C9:G9)+(DCF!G6*(1+G$5)/($B10-G$5))*DCF!G8)-Assumptions!$C$12)/Assumptions!$C$13*1000,-3)

Sheet Comps
B2: Trading Comps Cross-Check
B3: Illustrative peer-multiple triangulation; not the primary valuation method.
B5: Company | C5: Ticker | D5: Market | E5: EV/EBITDA | F5: P/E | G5: Notes
B6: Hoa Phat Group | C6: HPG VN | D6: Vietnam | E6: =DCF!C17/'Operating Forecast'!E8 | F6: =Assumptions!C14/('Operating Forecast'!E13/Assumptions!C13*1000) | G6: Subject company, model-implied
B7: Formosa Ha Tinh proxy | C7: Private | D7: Vietnam | E7: 7 | F7: 10.5 | G7: Illustrative integrated steel reference
B8: POSCO Holdings | C8: 005490 KS | D8: Korea | E8: 6.2 | F8: 9 | G8: Regional integrated steel peer
B9: Baoshan Iron & Steel | C9: 600019 CH | D9: China | E9: 5.8 | F9: 8.5 | G9: China steel peer; lower multiple due to supply cycle

Sheet Sources
B2: Sources & Notes
B3: Public inputs used for academic modeling; refresh before investment use.
B5: Topic | C5: Source | D5: Date / Period | E5: Model Use | F5: URL
B6: FY2025 operating base | C6: Hoa Phat Group Annual Report 2025 | D6: FY2025 | E6: Revenue, Dung Quat 2 ramp context | F6: https://file.hoaphat.com.vn/hoaphat-com-vn/2026/04/annual-report-2025-hpg.pdf
B7: Q1 2026 update | C7: Hoa Phat quarter summary via MarketScreener | D7: Q1 2026 | E7: Revenue/profit growth direction | F7: https://www.marketscreener.com/news/hoa-phat-quarter-summary-quarter-i-2026-ce7f58dad98ef221
B8: Market price | C8: Investing.com / TradingView / Yahoo Finance public quote pages | D8: Jun 2026 | E8: Spot price cross-check | F8: https://www.investing.com/equities/hoa-phat-group-jsc
B9: Broker triangulation | C9: Mirae Asset HPG update | D9: 2026 | E9: Revenue/margin direction cross-check | F9: https://masvn.com/api/attachment/file/1771843508095-EN_HPG_report_022326.pptx.pdf
B10: Model methodology | C10: Analyst assumptions | D10: 11-Jun-2026 | E10: WACC, terminal growth, capex normalization | F10: Internal academic model
